LICENSE
README.md
setup.cfg
setup.py
tether/__init__.py
tether/config.py
tether/exceptions.py
tether/manager.py
tether/models.py
tether/sources/__init__.py
tether/sources/arzpaya.py
tether/sources/base.py
tether/sources/bitbarg.py
tether/sources/hamtapay.py
tether/sources/wallex.py
tether_price.egg-info/PKG-INFO
tether_price.egg-info/SOURCES.txt
tether_price.egg-info/dependency_links.txt
tether_price.egg-info/requires.txt
tether_price.egg-info/top_level.txt